<Questions>
    <Question>
        <Style ElementAlign="NewLine" Indent="1" ZIndex="-1510">
            <Control Type="Edit"></Control>
        </Style>
        <Control Type="Edit" QuestionName="_QLABarcode__Page_QLAScan" ElementID="_Q0" Value="" Length="1000">
            <Style ElementAlign="NewLine" Indent="1" ZIndex="-1510">
                <Control Type="Edit"></Control>
            </Style>
        </Control>
        <Control Type="CheckButton" QuestionName="_QLABarcode__Page_QLAScan_X" ElementID="_Q0_X">
            <Style ElementAlign="NewLine" Indent="1">
                <Control Type="CheckButton"></Control>
            </Style>
            <Category Name="noproduct" CategoryID="0">
                <Label>
                    <Style ElementAlign="Right">
                        <Font IsBold="true"></Font>
                    </Style>
                    <Text>no matching product found</Text>
                </Label>
            </Category>
        </Control>
        <Control Type="CheckButton" QuestionName="_QLABarcode__Page_QLAScan_X" ElementID="_Q0_X">
            <Style ElementAlign="NewLine" Indent="1">
                <Control Type="CheckButton"></Control>
            </Style>
            <Category Name="noanswer" CategoryID="1">
                <Label>
                    <Style ElementAlign="Right">
                        <Font IsBold="true"></Font>
                    </Style>
                    <Text>no answer provided</Text>
                </Label>
            </Category>
        </Control>
    </Question>
</Questions>
