<Questions>
  <Question>
    <Style ElementAlign="NewLine" Indent="1" />
    <Table UseTablesLayout="0" Summary="xxx">
      <Row Y="0">
        <Cell X="0" Y="0">
          <Control Type="RadioButton" QuestionName="_QGenderReal_C" ElementID="_Q0_C">
            <Style ElementAlign="NewLine" Indent="1">
              <Control Type="RadioButton" />
            </Style>
            <Category Name="male" CategoryID="0">
              <Label>
                <Style ElementAlign="Right" />
                <Text>male</Text>
              </Label>
            </Category>
          </Control>
        </Cell>
      </Row>
      <Row Y="1">
        <Cell X="0" Y="1">
          <Control Type="RadioButton" QuestionName="_QGenderReal_C" ElementID="_Q0_C">
            <Style ElementAlign="NewLine" Indent="1">
              <Control Type="RadioButton" />
            </Style>
            <Category Name="female" CategoryID="1">
              <Label>
                <Style ElementAlign="Right" />
                <Text>female</Text>
              </Label>
            </Category>
          </Control>
        </Cell>
      </Row>
      <Row Y="2">
        <Cell X="0" Y="2">
          <Control Type="RadioButton" QuestionName="_QGenderReal_C" ElementID="_Q0_C">
            <Style ElementAlign="NewLine" Indent="1">
              <Control Type="RadioButton" />
            </Style>
            <Category Name="OtherGender" CategoryID="2">
              <Label>
                <Style ElementAlign="Right" />
                <Text>other please specify</Text>
              </Label>
            </Category>
          </Control>
          <Question>
            <Style ElementAlign="Right">
              <Control Type="SingleLinedEdit" />
            </Style>
            <Label ElementID="_Q0_O2">
              <Style ElementAlign="Right" />
            </Label>
            <Control Type="SingleLineEdit" QuestionName="_QGender_0othergender" ElementID="_Q0_O2" Value="" Length="1024">
              <Style ElementAlign="Right">
                <Control Type="SingleLineEdit" />
              </Style>
            </Control>
          </Question>
        </Cell>
      </Row>
    </Table>
  </Question>
</Questions>
